{"configuration":{"name":"mc-item-022398373670876026","title":"Modeling Cool and Warm Air","stem":"These models represent cool and warm air particles in a cube. The cool air particles move slowly. In the same volume of warm air, the particles move faster and are more spread out. Warm air is less dense than cool air.","stemImage":"","stemImageShown":false,"feedBack":{"attempts":"2","firstWrongHint":"","finalWrongHint":"","correctHint":""},"options":[{"image":"../../../../img/cards/ms_cnlese814295_4a_1.png","name":"mc-opt-item-028151441155932844","label":"cool air","value":"0","isCorrect":true,"id":"img1","checked":"checked"},{"image":"../../../../img/cards/ms_cnlese814295_4a_2.png","name":"mc-opt-item-06761015402153134x1","label":"warm air","value":"1","isCorrect":false,"id":"img2","checked":""}],"voiceOver":"","tipText":"","downloadLink":"","instantFeedback":false,"teacherAnswer":"","questionImage":""}}