{"ActivityTitle":"","QuestionStem":"<p class=\"quill-source-editor\">Think about Earth’s oceans as one subsystem within the larger Earth system. Describe at least two inputs and two outputs to the ocean subsystem. What are some interactions that the ocean has with other subsystems?</p>","Tip":"","Summary":"","no-SampleAnswer":"","SampleAnswer":"","InstructionText":"","no-InstructionText":"","qtype":"box","AudioFromRCE":false,"AllowAudio":true,"AllowFullScreen":true,"AllowRefresh":true,"isPracticeInteraction":false,"ShowToolbar":"false","ShowCharacterCount":"false","SampleAnswerMode":"stack","MaxCharacterLimit":"","Stimulus":{"image":{"src":"","no-src":"","credits":""},"text":{"src":""},"audio":{"src":"","caption":"","credit":""},"video":{"no-src":"","src":""}},"audioFile":"../../../../captions/audio/e52312727ca84c7a8c516e6e3264c109.json","audioSchema":"short_text_audio_schema.json","SummaryAltText":""}